cliquery/.cliqrc
cliquery/__init__.py
cliquery/bookmark.py
cliquery/cliquery.py
cliquery/config.py
cliquery/open.py
cliquery/pyteaser.py
cliquery/utils.py
cliquery-1.10.1.dist-info/LICENSE.txt
cliquery-1.10.1.dist-info/METADATA
cliquery-1.10.1.dist-info/WHEEL
cliquery-1.10.1.dist-info/entry_points.txt
cliquery-1.10.1.dist-info/top_level.txt
cliquery-1.10.1.dist-info/RECORD
