Metadata-Version: 2.1
Name: cliquery
Version: 1.10.1
Summary: a command-line browser interface
Home-page: https://github.com/huntrar/cliquery
Author: Hunter Hammond
Author-email: huntrar@gmail.com
Maintainer: Hunter Hammond
Maintainer-email: huntrar@gmail.com
License: MIT
Keywords: cliquery command line console help answer google bing search feeling lucky wolfram alpha knowledge engine scientific computation internet browser interface bookmark pyteaser preview
Platform: UNKNOWN
Classifier: Development Status :: 4 - Beta
Classifier: Environment :: Console
Classifier: Environment :: Web Environment
Classifier: Intended Audience :: End Users/Desktop
Classifier: Intended Audience :: Developers
Classifier: Intended Audience :: System Administrators
Classifier: License :: OSI Approved :: MIT License
Classifier: Operating System :: OS Independent
Classifier: Programming Language :: Python :: 3
Classifier: Programming Language :: Python :: 3.6
Classifier: Programming Language :: Python :: 3.7
Classifier: Programming Language :: Python :: 3.8
Classifier: Programming Language :: Python :: 3.9
Classifier: Topic :: Utilities
License-File: LICENSE.txt
Requires-Dist: lxml
Requires-Dist: requests
Requires-Dist: requests-cache
Requires-Dist: six
